webservices/__init__.py
webservices/async_helpers.py
webservices/exceptions.py
webservices/models.py
webservices/sync.py
webservices/tests.py
webservices/version.py
webservices.naudit-0.7.2.dist-info/LICENSE.txt
webservices.naudit-0.7.2.dist-info/METADATA
webservices.naudit-0.7.2.dist-info/WHEEL
webservices.naudit-0.7.2.dist-info/top_level.txt
webservices.naudit-0.7.2.dist-info/RECORD
