Metadata-Version: 2.1
Name: webservices.naudit
Version: 0.7.2
Summary: This is a fork from https://github.com/aldryncore/webservices. A web service library.
Author-email: Jonas Obrist <jonas@example.com>, Rafael Leira <rafael.leira@naudit.es>
License: BSD License
Project-URL: Homepage, https://github.com/Naudit/webservices
License-File: LICENSE.txt
Requires-Dist: itsdangerous
Provides-Extra: consumer
Requires-Dist: requests ; extra == 'consumer'
Provides-Extra: django
Requires-Dist: django ; extra == 'django'
Requires-Dist: requests ; extra == 'django'
Provides-Extra: flask
Requires-Dist: flask ; extra == 'flask'
Requires-Dist: requests ; extra == 'flask'
Provides-Extra: tests
Requires-Dist: twisted ; extra == 'tests'
Requires-Dist: requests ; extra == 'tests'
Requires-Dist: django ; extra == 'tests'
Requires-Dist: flask ; extra == 'tests'
Provides-Extra: twisted
Requires-Dist: twisted ; extra == 'twisted'
